hello/__init__.py
hello/main.py
hellozt-0.0.1.dist-info/METADATA
hellozt-0.0.1.dist-info/WHEEL
hellozt-0.0.1.dist-info/top_level.txt
hellozt-0.0.1.dist-info/RECORD
